INSTALL.rst
LICENSE
MANIFEST.in
README.rst
VERSION
requirements.txt
setup.py
tasks.py
src/sequtil/__init__.py
src/sequtil/__main__.py
src/sequtil/__meta__.py
src/sequtil/api.py
src/sequtil/api_generics.py
src/sequtil/tools.py
src/sequtil/utilities.py
src/sequtil.egg-info/PKG-INFO
src/sequtil.egg-info/SOURCES.txt
src/sequtil.egg-info/dependency_links.txt
src/sequtil.egg-info/not-zip-safe
src/sequtil.egg-info/requires.txt
src/sequtil.egg-info/top_level.txt
src/sequtil/listtypes/__init__.py
src/sequtil/listtypes/base.py
src/sequtil/listtypes/lazylist.py
src/sequtil/listtypes/linked.py
src/sequtil/listtypes/mappinglist.py
src/sequtil/listtypes/obslist.py
src/sequtil/listtypes/prevnextlist.py
src/sequtil/listtypes/sorted.py
src/sequtil/listtypes/taglist.py
src/sequtil/listtypes/userarray.py
src/sequtil/tests/__init__.py
src/sequtil/tests/__main__.py
src/sequtil/tests/test_documentation.py
src/sequtil/tests/test_sequtil.py